main.py
nepse_cli.py
nepse/__init__.py
nepse/config.py
nepse/core/__init__.py
nepse/core/auth.py
nepse/core/ipo.py
nepse/core/portfolio.py
nepse/services/__init__.py
nepse/services/market.py
nepse/ui/__init__.py
nepse/ui/cli.py
nepse/ui/console.py
nepse/ui/member_ui.py
nepse/utils/__init__.py
nepse/utils/browser.py
nepse/utils/formatting.py
nepse_cli-3.0.1.dist-info/licenses/LICENSE
nepse_cli-3.0.1.dist-info/METADATA
nepse_cli-3.0.1.dist-info/WHEEL
nepse_cli-3.0.1.dist-info/entry_points.txt
nepse_cli-3.0.1.dist-info/top_level.txt
nepse_cli-3.0.1.dist-info/RECORD
