Metadata-Version: 2.4
Name: nepse-cli
Version: 3.0.1
Summary: Modern CLI tool for Meroshare IPO automation and NEPSE market data with interactive TUI
Home-page: https://github.com/menaceXnadin/nepse-cli
Author: MenaceXnadin
Classifier: Development Status :: 4 - Beta
Classifier: Intended Audience :: End Users/Desktop
Classifier: License :: OSI Approved :: MIT License
Classifier: Programming Language :: Python :: 3
Classifier: Programming Language :: Python :: 3.7
Classifier: Programming Language :: Python :: 3.8
Classifier: Programming Language :: Python :: 3.9
Classifier: Programming Language :: Python :: 3.10
Classifier: Programming Language :: Python :: 3.11
Classifier: Programming Language :: Python :: 3.12
Requires-Python: >=3.7
License-File: LICENSE
Requires-Dist: playwright>=1.40.0
Requires-Dist: prompt_toolkit>=3.0.48
Requires-Dist: rich>=13.0.0
Requires-Dist: colorama>=0.4.6
Requires-Dist: requests>=2.25.0
Requires-Dist: beautifulsoup4>=4.9.0
Requires-Dist: cloudscraper>=1.2.0
Requires-Dist: tenacity>=9.0.0
Requires-Dist: lxml>=4.9.0
Dynamic: author
Dynamic: classifier
Dynamic: description
Dynamic: description-content-type
Dynamic: home-page
Dynamic: license-file
Dynamic: requires-dist
Dynamic: requires-python
Dynamic: summary
